{
  "captured_at": "20260504T192141Z",
  "request": {
    "method": "GET",
    "url": "https://web-static3.lovart.ai/lovart_prd/static/_next/static/chunks/03acpp0gdecc_.js",
    "path": "/lovart_prd/static/_next/static/chunks/03acpp0gdecc_.js",
    "headers": {
      "origin": "https://www.lovart.ai",
      "sec-ch-ua-platform": "\"macOS\"",
      "user-agent": "Mozilla/5.0 (Macintosh; Intel Mac OS X 10_15_7) AppleWebKit/537.36 (KHTML, like Gecko) Chrome/147.0.0.0 Safari/537.36",
      "sec-ch-ua": "\"Google Chrome\";v=\"147\", \"Not.A/Brand\";v=\"8\", \"Chromium\";v=\"147\"",
      "sec-ch-ua-mobile": "?0",
      "accept": "*/*",
      "sec-fetch-site": "same-site",
      "sec-fetch-mode": "cors",
      "sec-fetch-dest": "script",
      "referer": "https://www.lovart.ai/",
      "accept-encoding": "gzip, deflate, br, zstd",
      "accept-language": "zh,en;q=0.9,zh-CN;q=0.8",
      "if-modified-since": "Mon, 13 Apr 2026 09:59:30 GMT"
    },
    "body": null
  },
  "response": {
    "status_code": 304,
    "headers": {
      "date": "Mon, 04 May 2026 19:21:41 GMT",
      "server": "cloudflare",
      "age": "1844820",
      "x-oss-server-time": "12",
      "vary": "Accept-Encoding, Origin",
      "x-oss-request-id": "69DCCB70E37C95363823AE35",
      "access-control-allow-origin": "*",
      "access-control-allow-methods": "GET, POST, PUT, DELETE, HEAD",
      "access-control-max-age": "0",
      "last-modified": "Mon, 13 Apr 2026 09:59:30 GMT",
      "x-oss-object-type": "Normal",
      "x-oss-hash-crc64ecma": "10694193328065561035",
      "x-oss-storage-class": "Standard",
      "content-md5": "fy7stUnBYkzMbtQaRv1VWg==",
      "expires": "Mon, 04 May 2026 23:21:41 GMT",
      "cache-control": "public, max-age=14400",
      "cf-cache-status": "HIT",
      "set-cookie": "__cf_bm=lqq5KXvRUl8to6FSEIIc.cw6F4xUS4Ll2LzcJaCL574-1777922501.844511-1.0.1.1-gvr7Vs8Kz5zUY4a5NWDBhxU3vHP.nLMOZ_uUC2ktTtZ0AqsNd2ZDuTuXCKJX_LJIJ54rmH4GknvhNGNFbf7XUqJZbZ7Vy2wA9GYMxTnfaWMUyfl1VJRDdczY10ZYhtMz; HttpOnly; Secure; Path=/; Domain=lovart.ai; Expires=Mon, 04 May 2026 19:51:41 GMT",
      "access-control-expose-headers": "ETag, x-oss-request-id, x-oss-version-id",
      "cf-ray": "9f69deb48dc17076-NRT"
    },
    "body": null
  },
  "response_body": null
}