{
  "captured_at": "20260504T151042Z",
  "request": {
    "method": "GET",
    "url": "https://a.lovart.ai/artifacts/generator/GZatKZzB76AsJhWc.png?x-oss-process=image/resize,w_512,m_lfit/format,webp",
    "path": "/artifacts/generator/GZatKZzB76AsJhWc.png?x-oss-process=image/resize,w_512,m_lfit/format,webp",
    "headers": {
      "origin": "https://www.lovart.ai",
      "sec-ch-ua-platform": "\"macOS\"",
      "user-agent": "Mozilla/5.0 (Macintosh; Intel Mac OS X 10_15_7) AppleWebKit/537.36 (KHTML, like Gecko) Chrome/147.0.0.0 Safari/537.36",
      "sec-ch-ua": "\"Google Chrome\";v=\"147\", \"Not.A/Brand\";v=\"8\", \"Chromium\";v=\"147\"",
      "sec-ch-ua-mobile": "?0",
      "accept": "image/avif,image/webp,image/apng,image/svg+xml,image/*,*/*;q=0.8",
      "sec-fetch-site": "same-site",
      "sec-fetch-mode": "cors",
      "sec-fetch-dest": "image",
      "referer": "https://www.lovart.ai/",
      "accept-encoding": "gzip, deflate, br, zstd",
      "accept-language": "zh,en;q=0.9,zh-CN;q=0.8",
      "if-none-match": "\"75B0F246E0CD87AD915588BD6F6AFE3A\"",
      "if-modified-since": "Fri, 01 May 2026 10:18:21 GMT",
      "priority": "i"
    },
    "body": null
  },
  "response": {
    "status_code": 304,
    "headers": {
      "date": "Mon, 04 May 2026 15:10:42 GMT",
      "server": "cloudflare",
      "x-oss-server-time": "980",
      "age": "21620",
      "x-oss-request-id": "69F8627DBFFCAD37359159E4",
      "access-control-allow-origin": "*",
      "access-control-allow-methods": "GET, POST, PUT, DELETE, HEAD",
      "access-control-expose-headers": "ETag, x-oss-request-id, x-oss-version-id",
      "access-control-max-age": "0",
      "etag": "\"75B0F246E0CD87AD915588BD6F6AFE3A\"",
      "last-modified": "Fri, 01 May 2026 10:18:21 GMT",
      "x-oss-object-type": "Normal",
      "x-oss-storage-class": "Standard",
      "x-oss-version-id": "CAEQnQIYgYDAtOmXjO8ZIiAyM2QwOTM0YWU5ZTc0MjJjYWM0YjNmZWZmOTZlZmE4Ng--",
      "x-oss-hash-crc64ecma": "16142811242939152971",
      "expires": "Mon, 04 May 2026 19:10:42 GMT",
      "cache-control": "public, max-age=14400",
      "cf-cache-status": "HIT",
      "set-cookie": "__cf_bm=tEPN_EmimpIps2dh14AlXiaEQtm.us7KoWFn6uET368-1777907442.8656223-1.0.1.1-hGrZu0R30RHbeeS5v96.FyFc63d.djLK0I_afbApV1gPzWu0zhS3OE4zgpUe80U7uMGVKYz2WOVIN.C7VJgMhuZoJn1Vv7S9J5OGRfhynQEXwyFWPewAUxg3NwUYV_NY; HttpOnly; Secure; Path=/; Domain=lovart.ai; Expires=Mon, 04 May 2026 15:40:42 GMT",
      "content-disposition": "attachment",
      "content-security-policy": "sandbox allow-scripts",
      "cf-ray": "9f686f0de803bcca-HKG"
    },
    "body": null
  },
  "response_body": null
}